istatapi/__init__.py
istatapi/_modidx.py
istatapi/base.py
istatapi/discovery.py
istatapi/retrieval.py
istatapi/utils.py
istatapi-1.0.0.dist-info/LICENSE
istatapi-1.0.0.dist-info/METADATA
istatapi-1.0.0.dist-info/WHEEL
istatapi-1.0.0.dist-info/entry_points.txt
istatapi-1.0.0.dist-info/top_level.txt
istatapi-1.0.0.dist-info/RECORD
