Metadata-Version: 2.1
Name: istatapi
Version: 1.0.0
Summary: Python API for ISTAT (The Italian National Institute of Statistics)
Home-page: https://github.com/Attol8/istatapi
Author: Jacopo Attolini
Author-email: jacopoattolini@gmail.com
License: Apache Software License 2.0
Keywords: istat API python development datascience
Classifier: Development Status :: 3 - Alpha
Classifier: Intended Audience :: Developers
Classifier: Natural Language :: English
Classifier: Programming Language :: Python :: 3.7
Classifier: Programming Language :: Python :: 3.8
Classifier: Programming Language :: Python :: 3.9
Classifier: Programming Language :: Python :: 3.10
Classifier: License :: OSI Approved :: Apache Software License
Requires-Python: >=3.7
License-File: LICENSE
Requires-Dist: fastcore
Requires-Dist: pandas
Requires-Dist: requests
Requires-Dist: matplotlib
Requires-Dist: pyopenssl
Provides-Extra: dev
Requires-Dist: fastcore ; extra == 'dev'
Requires-Dist: pandas ; extra == 'dev'
Requires-Dist: requests ; extra == 'dev'
Requires-Dist: matplotlib ; extra == 'dev'
Requires-Dist: black ; extra == 'dev'
Requires-Dist: pyopenssl ; extra == 'dev'
